setup.py
tcr/AccountSupervisorService.py
tcr/AgeCheckService.py
tcr/AuthService.py
tcr/BotService.py
tcr/BuddyManagementService.py
tcr/BuddyService.py
tcr/CallService.py
tcr/ChannelApplicationProvidedService.py
tcr/ChannelService.py
tcr/MessageService.py
tcr/ShopService.py
tcr/SnsAdaptorService.py
tcr/SpotService.py
tcr/SquareService.py
tcr/TalkService.py
tcr/UniversalNotificationService.py
tcr/__init__.py
tcr/constants.py
tcr/ttypes.py
tcr.egg-info/PKG-INFO
tcr.egg-info/SOURCES.txt
tcr.egg-info/dependency_links.txt
tcr.egg-info/top_level.txt