Metadata-Version: 1.1
Name: tcr
Version: 0.1
Summary: A unofficial line bot lib
Home-page: https://github.com/surya-zxc/tcr
Author: Ahmad Suryani
Author-email: zxchidden@gmail.com
License: UNKNOWN
Keywords: unofficial,line-bot,test
Platform: UNKNOWN
Classifier: Programming Language :: Python
Classifier: Topic :: Internet :: WWW/HTTP :: Dynamic Content
Classifier: Topic :: Communications :: Chat
